{"name":"testing-game","className":"DataModel","filePaths":["default.project.json"],"children":[{"name":"Lighting","className":"Lighting"},{"name":"ReplicatedStorage","className":"ReplicatedStorage","filePaths":["src/shared/init.meta.json"],"children":[{"name":"Data","className":"Folder","children":[{"name":"DataTemplate","className":"ModuleScript","filePaths":["src/shared/Data/DataTemplate.luau"]}]},{"name":"Modules","className":"Folder","children":[{"name":"Explosion","className":"ModuleScript","filePaths":["src/shared/Modules/Explosion.luau"]},{"name":"Notifications","className":"ModuleScript","filePaths":["src/shared/Modules/Notifications.luau"]},{"name":"Ragdoll","className":"ModuleScript","filePaths":["src/shared/Modules/Ragdoll.luau"]},{"name":"Utils","className":"Folder","children":[{"name":"Cooldowns","className":"ModuleScript","filePaths":["src/shared/Modules/Utils/Cooldowns.luau"]},{"name":"Formatters","className":"ModuleScript","filePaths":["src/shared/Modules/Utils/Formatters.luau"]},{"name":"SoundUtils","className":"ModuleScript","filePaths":["src/shared/Modules/Utils/SoundUtils.luau"]},{"name":"TypeUtils","className":"ModuleScript","filePaths":["src/shared/Modules/Utils/TypeUtils.luau"]}]},{"name":"Weapon","className":"Folder","children":[{"name":"UI","className":"Folder","children":[{"name":"App","className":"ModuleScript","filePaths":["src/shared/Modules/Weapon/UI/App.luau"]},{"name":"Store","className":"ModuleScript","filePaths":["src/shared/Modules/Weapon/UI/Store.luau"]}]},{"name":"WeaponConfigs","className":"Folder","children":[{"name":"RPG","className":"ModuleScript","filePaths":["src/shared/Modules/Weapon/WeaponConfigs/RPG.luau"]},{"name":"Revolver","className":"ModuleScript","filePaths":["src/shared/Modules/Weapon/WeaponConfigs/Revolver.luau"]},{"name":"_types","className":"ModuleScript","filePaths":["src/shared/Modules/Weapon/WeaponConfigs/_types.luau"]}]},{"name":"WeaponTypes","className":"Folder","children":[{"name":"BulletWeapon","className":"Folder","children":[{"name":"BulletWeapon","className":"ModuleScript","filePaths":["src/shared/Modules/Weapon/WeaponTypes/BulletWeapon/BulletWeapon.luau"]},{"name":"_types","className":"ModuleScript","filePaths":["src/shared/Modules/Weapon/WeaponTypes/BulletWeapon/_types.luau"]}]},{"name":"RPGWeapon","className":"Folder","children":[{"name":"RPGWeapon","className":"ModuleScript","filePaths":["src/shared/Modules/Weapon/WeaponTypes/RPGWeapon/RPGWeapon.luau"]},{"name":"_types","className":"ModuleScript","filePaths":["src/shared/Modules/Weapon/WeaponTypes/RPGWeapon/_types.luau"]}]}]},{"name":"WeaponUtils","className":"ModuleScript","filePaths":["src/shared/Modules/Weapon/WeaponUtils.luau"]},{"name":"WeaponsNetwork","className":"ModuleScript","filePaths":["src/shared/Modules/Weapon/WeaponsNetwork.luau"]},{"name":"WeaponsSystem","className":"ModuleScript","filePaths":["src/shared/Modules/Weapon/WeaponsSystem.luau"]}]}]},{"name":"Network","className":"ModuleScript","filePaths":["src/shared/Network.luau"]},{"name":"UI","className":"Folder","children":[{"name":"App","className":"ModuleScript","filePaths":["src/shared/UI/App.luau"]},{"name":"Components","className":"Folder","children":[{"name":"Base","className":"Folder","children":[{"name":"Button","className":"ModuleScript","filePaths":["src/shared/UI/Components/Base/Button.luau"]},{"name":"Frame","className":"ModuleScript","filePaths":["src/shared/UI/Components/Base/Frame.luau"]},{"name":"LoadingSpinner","className":"ModuleScript","filePaths":["src/shared/UI/Components/Base/LoadingSpinner.luau"]},{"name":"MenuButton","className":"ModuleScript","filePaths":["src/shared/UI/Components/Base/MenuButton.luau"]}]},{"name":"Cash","className":"Folder","children":[{"name":"CashDisplay","className":"ModuleScript","filePaths":["src/shared/UI/Components/Cash/CashDisplay.luau"]},{"name":"CashNotifications","className":"ModuleScript","filePaths":["src/shared/UI/Components/Cash/CashNotifications.luau"]}]},{"name":"Menu","className":"Folder","children":[{"name":"MenuContainer","className":"ModuleScript","filePaths":["src/shared/UI/Components/Menu/MenuContainer.luau"]}]}]},{"name":"Composables","className":"Folder","children":[{"name":"tween","className":"ModuleScript","filePaths":["src/shared/UI/Composables/tween.luau"]},{"name":"useEvent","className":"ModuleScript","filePaths":["src/shared/UI/Composables/useEvent.luau"]},{"name":"usePx","className":"ModuleScript","filePaths":["src/shared/UI/Composables/usePx.luau"]}]},{"name":"Stores","className":"Folder","children":[{"name":"PlayerData","className":"ModuleScript","filePaths":["src/shared/UI/Stores/PlayerData.luau"]}]},{"name":"Theme","className":"ModuleScript","filePaths":["src/shared/UI/Theme/init.luau"],"children":[{"name":"Tokens","className":"Folder","children":[{"name":"Backgrounds","className":"ModuleScript","filePaths":["src/shared/UI/Theme/Tokens/Backgrounds.luau"]},{"name":"Colors","className":"ModuleScript","filePaths":["src/shared/UI/Theme/Tokens/Colors.luau"]},{"name":"Fonts","className":"ModuleScript","filePaths":["src/shared/UI/Theme/Tokens/Fonts.luau"]},{"name":"Radii","className":"ModuleScript","filePaths":["src/shared/UI/Theme/Tokens/Radii.luau"]},{"name":"Stroke","className":"ModuleScript","filePaths":["src/shared/UI/Theme/Tokens/Stroke.luau"]}]}]},{"name":"Views","className":"Folder","children":[{"name":"PunishmentPanel","className":"ModuleScript","filePaths":["src/shared/UI/Views/PunishmentPanel.luau"]},{"name":"Wallet","className":"ModuleScript","filePaths":["src/shared/UI/Views/Wallet.luau"]}]}]},{"name":"Packages","className":"Folder","children":[{"name":"Charm","className":"ModuleScript","filePaths":["Packages/Charm.lua"]},{"name":"Component","className":"ModuleScript","filePaths":["Packages/Component.lua"]},{"name":"Conch","className":"ModuleScript","filePaths":["Packages/Conch.lua"]},{"name":"ConchUI","className":"ModuleScript","filePaths":["Packages/ConchUI.lua"]},{"name":"FastCast","className":"ModuleScript","filePaths":["Packages/FastCast.lua"]},{"name":"GreenTea","className":"ModuleScript","filePaths":["Packages/GreenTea.lua"]},{"name":"Iris","className":"ModuleScript","filePaths":["Packages/Iris.lua"]},{"name":"Loader","className":"ModuleScript","filePaths":["Packages/Loader.lua"]},{"name":"LucideIcons","className":"ModuleScript","filePaths":["Packages/LucideIcons.lua"]},{"name":"Lyra","className":"ModuleScript","filePaths":["Packages/Lyra.lua"]},{"name":"Promise","className":"ModuleScript","filePaths":["Packages/Promise.lua"]},{"name":"Remo","className":"ModuleScript","filePaths":["Packages/Remo.lua"]},{"name":"Replica","className":"ModuleScript","filePaths":["Packages/Replica.lua"]},{"name":"Sift","className":"ModuleScript","filePaths":["Packages/Sift.lua"]},{"name":"Signal","className":"ModuleScript","filePaths":["Packages/Signal.lua"]},{"name":"Trove","className":"ModuleScript","filePaths":["Packages/Trove.lua"]},{"name":"Vide","className":"ModuleScript","filePaths":["Packages/Vide.lua"]},{"name":"VideCharm","className":"ModuleScript","filePaths":["Packages/VideCharm.lua"]},{"name":"_Index","className":"Folder","children":[{"name":"alicesaidhi_conch-language@0.3.1","className":"Folder","children":[{"name":"conch-language","className":"ModuleScript","filePaths":["Packages/_Index/alicesaidhi_conch-language@0.3.1/conch-language/dist/init.luau","Packages/_Index/alicesaidhi_conch-language@0.3.1/conch-language/default.project.json"],"children":[{"name":"lib","className":"ModuleScript","filePaths":["Packages/_Index/alicesaidhi_conch-language@0.3.1/conch-language/dist/lib.luau"]},{"name":"luau_packages","className":"Folder"},{"name":"roblox_packages","className":"Folder"},{"name":"src","className":"ModuleScript","filePaths":["Packages/_Index/alicesaidhi_conch-language@0.3.1/conch-language/dist/src/init.luau"],"children":[{"name":"analysis","className":"ModuleScript","filePaths":["Packages/_Index/alicesaidhi_conch-language@0.3.1/conch-language/dist/src/analysis/init.luau"]},{"name":"ast","className":"ModuleScript","filePaths":["Packages/_Index/alicesaidhi_conch-language@0.3.1/conch-language/dist/src/ast/init.luau"],"children":[{"name":"ast","className":"ModuleScript","filePaths":["Packages/_Index/alicesaidhi_conch-language@0.3.1/conch-language/dist/src/ast/ast.luau"]},{"name":"parse","className":"ModuleScript","filePaths":["Packages/_Index/alicesaidhi_conch-language@0.3.1/conch-language/dist/src/ast/parse.luau"]},{"name":"visit","className":"ModuleScript","filePaths":["Packages/_Index/alicesaidhi_conch-language@0.3.1/conch-language/dist/src/ast/visit.luau"]}]},{"name":"treewalker","className":"ModuleScript","filePaths":["Packages/_Index/alicesaidhi_conch-language@0.3.1/conch-language/dist/src/treewalker/init.luau"]}]}]}]},{"name":"alicesaidhi_conch-ui@0.3.1","className":"Folder","children":[{"name":"conch-ui","className":"ModuleScript","filePaths":["Packages/_Index/alicesaidhi_conch-ui@0.3.1/conch-ui/dist/init.luau","Packages/_Index/alicesaidhi_conch-ui@0.3.1/conch-ui/default.project.json"],"children":[{"name":"lib","className":"ModuleScript","filePaths":["Packages/_Index/alicesaidhi_conch-ui@0.3.1/conch-ui/dist/lib.luau"]},{"name":"luau_packages","className":"Folder"},{"name":"roblox_packages","className":"Folder","children":[{"name":"conch","className":"ModuleScript","filePaths":["Packages/_Index/alicesaidhi_conch-ui@0.3.1/conch-ui/dist/roblox_packages/conch.luau"]},{"name":"language","className":"ModuleScript","filePaths":["Packages/_Index/alicesaidhi_conch-ui@0.3.1/conch-ui/dist/roblox_packages/language.luau"]},{"name":"vide","className":"ModuleScript","filePaths":["Packages/_Index/alicesaidhi_conch-ui@0.3.1/conch-ui/dist/roblox_packages/vide.luau"]}]},{"name":"src","className":"ModuleScript","filePaths":["Packages/_Index/alicesaidhi_conch-ui@0.3.1/conch-ui/dist/src/init.luau"],"children":[{"name":"app","className":"ModuleScript","filePaths":["Packages/_Index/alicesaidhi_conch-ui@0.3.1/conch-ui/dist/src/app.luau"]},{"name":"components","className":"Folder","children":[{"name":"background","className":"ModuleScript","filePaths":["Packages/_Index/alicesaidhi_conch-ui@0.3.1/conch-ui/dist/src/components/background.luau"]},{"name":"container","className":"ModuleScript","filePaths":["Packages/_Index/alicesaidhi_conch-ui@0.3.1/conch-ui/dist/src/components/container.luau"]},{"name":"corner","className":"ModuleScript","filePaths":["Packages/_Index/alicesaidhi_conch-ui@0.3.1/conch-ui/dist/src/components/corner.luau"]},{"name":"flex","className":"ModuleScript","filePaths":["Packages/_Index/alicesaidhi_conch-ui@0.3.1/conch-ui/dist/src/components/flex.luau"]},{"name":"gap","className":"ModuleScript","filePaths":["Packages/_Index/alicesaidhi_conch-ui@0.3.1/conch-ui/dist/src/components/gap.luau"]},{"name":"loading","className":"ModuleScript","filePaths":["Packages/_Index/alicesaidhi_conch-ui@0.3.1/conch-ui/dist/src/components/loading.luau"]},{"name":"padding","className":"ModuleScript","filePaths":["Packages/_Index/alicesaidhi_conch-ui@0.3.1/conch-ui/dist/src/components/padding.luau"]},{"name":"screen","className":"ModuleScript","filePaths":["Packages/_Index/alicesaidhi_conch-ui@0.3.1/conch-ui/dist/src/components/screen.luau"]},{"name":"stroke","className":"ModuleScript","filePaths":["Packages/_Index/alicesaidhi_conch-ui@0.3.1/conch-ui/dist/src/components/stroke.luau"]},{"name":"suggestion","className":"ModuleScript","filePaths":["Packages/_Index/alicesaidhi_conch-ui@0.3.1/conch-ui/dist/src/components/suggestion.luau"]},{"name":"text","className":"ModuleScript","filePaths":["Packages/_Index/alicesaidhi_conch-ui@0.3.1/conch-ui/dist/src/components/text.luau"]},{"name":"textbox","className":"ModuleScript","filePaths":["Packages/_Index/alicesaidhi_conch-ui@0.3.1/conch-ui/dist/src/components/textbox.luau"]}]},{"name":"levenshtein_distance","className":"ModuleScript","filePaths":["Packages/_Index/alicesaidhi_conch-ui@0.3.1/conch-ui/dist/src/levenshtein_distance.luau"]},{"name":"state","className":"ModuleScript","filePaths":["Packages/_Index/alicesaidhi_conch-ui@0.3.1/conch-ui/dist/src/state.luau"]},{"name":"theme","className":"ModuleScript","filePaths":["Packages/_Index/alicesaidhi_conch-ui@0.3.1/conch-ui/dist/src/theme.luau"]}]}]},{"name":"conch","className":"ModuleScript","filePaths":["Packages/_Index/alicesaidhi_conch-ui@0.3.1/conch.lua"]},{"name":"language","className":"ModuleScript","filePaths":["Packages/_Index/alicesaidhi_conch-ui@0.3.1/language.lua"]},{"name":"vide","className":"ModuleScript","filePaths":["Packages/_Index/alicesaidhi_conch-ui@0.3.1/vide.lua"]}]},{"name":"alicesaidhi_conch@0.3.1","className":"Folder","children":[{"name":"conch","className":"ModuleScript","filePaths":["Packages/_Index/alicesaidhi_conch@0.3.1/conch/dist/init.luau","Packages/_Index/alicesaidhi_conch@0.3.1/conch/default.project.json"],"children":[{"name":"lib","className":"ModuleScript","filePaths":["Packages/_Index/alicesaidhi_conch@0.3.1/conch/dist/lib.luau"]},{"name":"luau_packages","className":"Folder"},{"name":"roblox_packages","className":"Folder","children":[{"name":"language","className":"ModuleScript","filePaths":["Packages/_Index/alicesaidhi_conch@0.3.1/conch/dist/roblox_packages/language.luau"]}]},{"name":"src","className":"ModuleScript","filePaths":["Packages/_Index/alicesaidhi_conch@0.3.1/conch/dist/src/init.luau"],"children":[{"name":"arguments","className":"ModuleScript","filePaths":["Packages/_Index/alicesaidhi_conch@0.3.1/conch/dist/src/arguments.luau"]},{"name":"bootstrap","className":"ModuleScript","filePaths":["Packages/_Index/alicesaidhi_conch@0.3.1/conch/dist/src/bootstrap.luau"]},{"name":"client","className":"ModuleScript","filePaths":["Packages/_Index/alicesaidhi_conch@0.3.1/conch/dist/src/client.luau"]},{"name":"console","className":"ModuleScript","filePaths":["Packages/_Index/alicesaidhi_conch@0.3.1/conch/dist/src/console.luau"]},{"name":"constants","className":"ModuleScript","filePaths":["Packages/_Index/alicesaidhi_conch@0.3.1/conch/dist/src/constants.luau"]},{"name":"context","className":"ModuleScript","filePaths":["Packages/_Index/alicesaidhi_conch@0.3.1/conch/dist/src/context.luau"]},{"name":"net","className":"ModuleScript","filePaths":["Packages/_Index/alicesaidhi_conch@0.3.1/conch/dist/src/net.luau"]},{"name":"signal","className":"ModuleScript","filePaths":["Packages/_Index/alicesaidhi_conch@0.3.1/conch/dist/src/signal.luau"]},{"name":"state","className":"ModuleScript","filePaths":["Packages/_Index/alicesaidhi_conch@0.3.1/conch/dist/src/state.luau"]},{"name":"types","className":"ModuleScript","filePaths":["Packages/_Index/alicesaidhi_conch@0.3.1/conch/dist/src/types.luau"]},{"name":"user","className":"ModuleScript","filePaths":["Packages/_Index/alicesaidhi_conch@0.3.1/conch/dist/src/user.luau"]}]}]},{"name":"language","className":"ModuleScript","filePaths":["Packages/_Index/alicesaidhi_conch@0.3.1/language.lua"]}]},{"name":"azutreo_replica@1.0.1","className":"Folder","children":[{"name":"replica","className":"ModuleScript","filePaths":["Packages/_Index/azutreo_replica@1.0.1/replica/src/init.luau","Packages/_Index/azutreo_replica@1.0.1/replica/default.project.json"],"children":[{"name":"ReplicaClient","className":"ModuleScript","filePaths":["Packages/_Index/azutreo_replica@1.0.1/replica/src/ReplicaClient.luau"]},{"name":"ReplicaServer","className":"ModuleScript","filePaths":["Packages/_Index/azutreo_replica@1.0.1/replica/src/ReplicaServer.luau"]},{"name":"ReplicaShared","className":"Folder","children":[{"name":"Maid","className":"ModuleScript","filePaths":["Packages/_Index/azutreo_replica@1.0.1/replica/src/ReplicaShared/Maid.luau"]},{"name":"RateLimit","className":"ModuleScript","filePaths":["Packages/_Index/azutreo_replica@1.0.1/replica/src/ReplicaShared/RateLimit.luau"]},{"name":"Remote","className":"ModuleScript","filePaths":["Packages/_Index/azutreo_replica@1.0.1/replica/src/ReplicaShared/Remote.luau"]},{"name":"Signal","className":"ModuleScript","filePaths":["Packages/_Index/azutreo_replica@1.0.1/replica/src/ReplicaShared/Signal.luau"]}]}]}]},{"name":"centau_vide@0.3.1","className":"Folder","children":[{"name":"vide","className":"ModuleScript","filePaths":["Packages/_Index/centau_vide@0.3.1/vide/src/init.luau","Packages/_Index/centau_vide@0.3.1/vide/default.project.json"],"children":[{"name":"action","className":"ModuleScript","filePaths":["Packages/_Index/centau_vide@0.3.1/vide/src/action.luau"]},{"name":"apply","className":"ModuleScript","filePaths":["Packages/_Index/centau_vide@0.3.1/vide/src/apply.luau"]},{"name":"batch","className":"ModuleScript","filePaths":["Packages/_Index/centau_vide@0.3.1/vide/src/batch.luau"]},{"name":"bind","className":"ModuleScript","filePaths":["Packages/_Index/centau_vide@0.3.1/vide/src/bind.luau"]},{"name":"changed","className":"ModuleScript","filePaths":["Packages/_Index/centau_vide@0.3.1/vide/src/changed.luau"]},{"name":"cleanup","className":"ModuleScript","filePaths":["Packages/_Index/centau_vide@0.3.1/vide/src/cleanup.luau"]},{"name":"context","className":"ModuleScript","filePaths":["Packages/_Index/centau_vide@0.3.1/vide/src/context.luau"]},{"name":"create","className":"ModuleScript","filePaths":["Packages/_Index/centau_vide@0.3.1/vide/src/create.luau"]},{"name":"defaults","className":"ModuleScript","filePaths":["Packages/_Index/centau_vide@0.3.1/vide/src/defaults.luau"]},{"name":"derive","className":"ModuleScript","filePaths":["Packages/_Index/centau_vide@0.3.1/vide/src/derive.luau"]},{"name":"effect","className":"ModuleScript","filePaths":["Packages/_Index/centau_vide@0.3.1/vide/src/effect.luau"]},{"name":"flags","className":"ModuleScript","filePaths":["Packages/_Index/centau_vide@0.3.1/vide/src/flags.luau"]},{"name":"graph","className":"ModuleScript","filePaths":["Packages/_Index/centau_vide@0.3.1/vide/src/graph.luau"]},{"name":"maps","className":"ModuleScript","filePaths":["Packages/_Index/centau_vide@0.3.1/vide/src/maps.luau"]},{"name":"mount","className":"ModuleScript","filePaths":["Packages/_Index/centau_vide@0.3.1/vide/src/mount.luau"]},{"name":"read","className":"ModuleScript","filePaths":["Packages/_Index/centau_vide@0.3.1/vide/src/read.luau"]},{"name":"root","className":"ModuleScript","filePaths":["Packages/_Index/centau_vide@0.3.1/vide/src/root.luau"]},{"name":"show","className":"ModuleScript","filePaths":["Packages/_Index/centau_vide@0.3.1/vide/src/show.luau"]},{"name":"source","className":"ModuleScript","filePaths":["Packages/_Index/centau_vide@0.3.1/vide/src/source.luau"]},{"name":"spring","className":"ModuleScript","filePaths":["Packages/_Index/centau_vide@0.3.1/vide/src/spring.luau"]},{"name":"switch","className":"ModuleScript","filePaths":["Packages/_Index/centau_vide@0.3.1/vide/src/switch.luau"]},{"name":"throw","className":"ModuleScript","filePaths":["Packages/_Index/centau_vide@0.3.1/vide/src/throw.luau"]},{"name":"untrack","className":"ModuleScript","filePaths":["Packages/_Index/centau_vide@0.3.1/vide/src/untrack.luau"]}]}]},{"name":"corecii_greentea@0.4.11","className":"Folder","children":[{"name":"greentea","className":"ModuleScript","filePaths":["Packages/_Index/corecii_greentea@0.4.11/greentea/src/init.luau","Packages/_Index/corecii_greentea@0.4.11/greentea/default.project.json"],"children":[{"name":"GreenTea","className":"ModuleScript","filePaths":["Packages/_Index/corecii_greentea@0.4.11/greentea/src/GreenTea.luau"]},{"name":"InstanceClasses","className":"ModuleScript","filePaths":["Packages/_Index/corecii_greentea@0.4.11/greentea/src/InstanceClasses.luau"]},{"name":"tCompat","className":"ModuleScript","filePaths":["Packages/_Index/corecii_greentea@0.4.11/greentea/src/tCompat.luau"]}]}]},{"name":"csqrl_sift@0.0.11","className":"Folder","children":[{"name":"sift","className":"ModuleScript","filePaths":["Packages/_Index/csqrl_sift@0.0.11/sift/src/init.lua","Packages/_Index/csqrl_sift@0.0.11/sift/default.project.json"],"children":[{"name":"Array","className":"ModuleScript","filePaths":["Packages/_Index/csqrl_sift@0.0.11/sift/src/Array/init.lua"],"children":[{"name":"at","className":"ModuleScript","filePaths":["Packages/_Index/csqrl_sift@0.0.11/sift/src/Array/at.lua"]},{"name":"concat","className":"ModuleScript","filePaths":["Packages/_Index/csqrl_sift@0.0.11/sift/src/Array/concat.lua"]},{"name":"concatDeep","className":"ModuleScript","filePaths":["Packages/_Index/csqrl_sift@0.0.11/sift/src/Array/concatDeep.lua"]},{"name":"copy","className":"ModuleScript","filePaths":["Packages/_Index/csqrl_sift@0.0.11/sift/src/Array/copy.lua"]},{"name":"copyDeep","className":"ModuleScript","filePaths":["Packages/_Index/csqrl_sift@0.0.11/sift/src/Array/copyDeep.lua"]},{"name":"count","className":"ModuleScript","filePaths":["Packages/_Index/csqrl_sift@0.0.11/sift/src/Array/count.lua"]},{"name":"create","className":"ModuleScript","filePaths":["Packages/_Index/csqrl_sift@0.0.11/sift/src/Array/create.lua"]},{"name":"dedupe","className":"ModuleScript","filePaths":["Packages/_Index/csqrl_sift@0.0.11/sift/src/Array/dedupe.luau"]},{"name":"difference","className":"ModuleScript","filePaths":["Packages/_Index/csqrl_sift@0.0.11/sift/src/Array/difference.lua"]},{"name":"differenceSymmetric","className":"ModuleScript","filePaths":["Packages/_Index/csqrl_sift@0.0.11/sift/src/Array/differenceSymmetric.lua"]},{"name":"equals","className":"ModuleScript","filePaths":["Packages/_Index/csqrl_sift@0.0.11/sift/src/Array/equals.lua"]},{"name":"equalsDeep","className":"ModuleScript","filePaths":["Packages/_Index/csqrl_sift@0.0.11/sift/src/Array/equalsDeep.lua"]},{"name":"every","className":"ModuleScript","filePaths":["Packages/_Index/csqrl_sift@0.0.11/sift/src/Array/every.lua"]},{"name":"filter","className":"ModuleScript","filePaths":["Packages/_Index/csqrl_sift@0.0.11/sift/src/Array/filter.lua"]},{"name":"find","className":"ModuleScript","filePaths":["Packages/_Index/csqrl_sift@0.0.11/sift/src/Array/find.lua"]},{"name":"findLast","className":"ModuleScript","filePaths":["Packages/_Index/csqrl_sift@0.0.11/sift/src/Array/findLast.lua"]},{"name":"findWhere","className":"ModuleScript","filePaths":["Packages/_Index/csqrl_sift@0.0.11/sift/src/Array/findWhere.lua"]},{"name":"findWhereLast","className":"ModuleScript","filePaths":["Packages/_Index/csqrl_sift@0.0.11/sift/src/Array/findWhereLast.lua"]},{"name":"first","className":"ModuleScript","filePaths":["Packages/_Index/csqrl_sift@0.0.11/sift/src/Array/first.lua"]},{"name":"flatten","className":"ModuleScript","filePaths":["Packages/_Index/csqrl_sift@0.0.11/sift/src/Array/flatten.lua"]},{"name":"freeze","className":"ModuleScript","filePaths":["Packages/_Index/csqrl_sift@0.0.11/sift/src/Array/freeze.lua"]},{"name":"freezeDeep","className":"ModuleScript","filePaths":["Packages/_Index/csqrl_sift@0.0.11/sift/src/Array/freezeDeep.lua"]},{"name":"includes","className":"ModuleScript","filePaths":["Packages/_Index/csqrl_sift@0.0.11/sift/src/Array/includes.lua"]},{"name":"insert","className":"ModuleScript","filePaths":["Packages/_Index/csqrl_sift@0.0.11/sift/src/Array/insert.lua"]},{"name":"is","className":"ModuleScript","filePaths":["Packages/_Index/csqrl_sift@0.0.11/sift/src/Array/is.lua"]},{"name":"last","className":"ModuleScript","filePaths":["Packages/_Index/csqrl_sift@0.0.11/sift/src/Array/last.lua"]},{"name":"map","className":"ModuleScript","filePaths":["Packages/_Index/csqrl_sift@0.0.11/sift/src/Array/map.lua"]},{"name":"pop","className":"ModuleScript","filePaths":["Packages/_Index/csqrl_sift@0.0.11/sift/src/Array/pop.lua"]},{"name":"push","className":"ModuleScript","filePaths":["Packages/_Index/csqrl_sift@0.0.11/sift/src/Array/push.lua"]},{"name":"reduce","className":"ModuleScript","filePaths":["Packages/_Index/csqrl_sift@0.0.11/sift/src/Array/reduce.lua"]},{"name":"reduceRight","className":"ModuleScript","filePaths":["Packages/_Index/csqrl_sift@0.0.11/sift/src/Array/reduceRight.lua"]},{"name":"removeIndex","className":"ModuleScript","filePaths":["Packages/_Index/csqrl_sift@0.0.11/sift/src/Array/removeIndex.lua"]},{"name":"removeIndices","className":"ModuleScript","filePaths":["Packages/_Index/csqrl_sift@0.0.11/sift/src/Array/removeIndices.lua"]},{"name":"removeValue","className":"ModuleScript","filePaths":["Packages/_Index/csqrl_sift@0.0.11/sift/src/Array/removeValue.lua"]},{"name":"removeValues","className":"ModuleScript","filePaths":["Packages/_Index/csqrl_sift@0.0.11/sift/src/Array/removeValues.lua"]},{"name":"reverse","className":"ModuleScript","filePaths":["Packages/_Index/csqrl_sift@0.0.11/sift/src/Array/reverse.lua"]},{"name":"set","className":"ModuleScript","filePaths":["Packages/_Index/csqrl_sift@0.0.11/sift/src/Array/set.lua"]},{"name":"shift","className":"ModuleScript","filePaths":["Packages/_Index/csqrl_sift@0.0.11/sift/src/Array/shift.lua"]},{"name":"shuffle","className":"ModuleScript","filePaths":["Packages/_Index/csqrl_sift@0.0.11/sift/src/Array/shuffle.lua"]},{"name":"slice","className":"ModuleScript","filePaths":["Packages/_Index/csqrl_sift@0.0.11/sift/src/Array/slice.lua"]},{"name":"some","className":"ModuleScript","filePaths":["Packages/_Index/csqrl_sift@0.0.11/sift/src/Array/some.lua"]},{"name":"sort","className":"ModuleScript","filePaths":["Packages/_Index/csqrl_sift@0.0.11/sift/src/Array/sort.lua"]},{"name":"splice","className":"ModuleScript","filePaths":["Packages/_Index/csqrl_sift@0.0.11/sift/src/Array/splice.lua"]},{"name":"toSet","className":"ModuleScript","filePaths":["Packages/_Index/csqrl_sift@0.0.11/sift/src/Array/toSet.lua"]},{"name":"unshift","className":"ModuleScript","filePaths":["Packages/_Index/csqrl_sift@0.0.11/sift/src/Array/unshift.lua"]},{"name":"update","className":"ModuleScript","filePaths":["Packages/_Index/csqrl_sift@0.0.11/sift/src/Array/update.lua"]},{"name":"zip","className":"ModuleScript","filePaths":["Packages/_Index/csqrl_sift@0.0.11/sift/src/Array/zip.lua"]},{"name":"zipAll","className":"ModuleScript","filePaths":["Packages/_Index/csqrl_sift@0.0.11/sift/src/Array/zipAll.lua"]}]},{"name":"Dictionary","className":"ModuleScript","filePaths":["Packages/_Index/csqrl_sift@0.0.11/sift/src/Dictionary/init.lua"],"children":[{"name":"copy","className":"ModuleScript","filePaths":["Packages/_Index/csqrl_sift@0.0.11/sift/src/Dictionary/copy.lua"]},{"name":"copyDeep","className":"ModuleScript","filePaths":["Packages/_Index/csqrl_sift@0.0.11/sift/src/Dictionary/copyDeep.lua"]},{"name":"count","className":"ModuleScript","filePaths":["Packages/_Index/csqrl_sift@0.0.11/sift/src/Dictionary/count.lua"]},{"name":"entries","className":"ModuleScript","filePaths":["Packages/_Index/csqrl_sift@0.0.11/sift/src/Dictionary/entries.lua"]},{"name":"equals","className":"ModuleScript","filePaths":["Packages/_Index/csqrl_sift@0.0.11/sift/src/Dictionary/equals.lua"]},{"name":"equalsDeep","className":"ModuleScript","filePaths":["Packages/_Index/csqrl_sift@0.0.11/sift/src/Dictionary/equalsDeep.lua"]},{"name":"every","className":"ModuleScript","filePaths":["Packages/_Index/csqrl_sift@0.0.11/sift/src/Dictionary/every.lua"]},{"name":"filter","className":"ModuleScript","filePaths":["Packages/_Index/csqrl_sift@0.0.11/sift/src/Dictionary/filter.lua"]},{"name":"flatten","className":"ModuleScript","filePaths":["Packages/_Index/csqrl_sift@0.0.11/sift/src/Dictionary/flatten.lua"]},{"name":"flip","className":"ModuleScript","filePaths":["Packages/_Index/csqrl_sift@0.0.11/sift/src/Dictionary/flip.lua"]},{"name":"freeze","className":"ModuleScript","filePaths":["Packages/_Index/csqrl_sift@0.0.11/sift/src/Dictionary/freeze.lua"]},{"name":"freezeDeep","className":"ModuleScript","filePaths":["Packages/_Index/csqrl_sift@0.0.11/sift/src/Dictionary/freezeDeep.lua"]},{"name":"fromArrays","className":"ModuleScript","filePaths":["Packages/_Index/csqrl_sift@0.0.11/sift/src/Dictionary/fromArrays.lua"]},{"name":"fromEntries","className":"ModuleScript","filePaths":["Packages/_Index/csqrl_sift@0.0.11/sift/src/Dictionary/fromEntries.lua"]},{"name":"has","className":"ModuleScript","filePaths":["Packages/_Index/csqrl_sift@0.0.11/sift/src/Dictionary/has.lua"]},{"name":"includes","className":"ModuleScript","filePaths":["Packages/_Index/csqrl_sift@0.0.11/sift/src/Dictionary/includes.lua"]},{"name":"keys","className":"ModuleScript","filePaths":["Packages/_Index/csqrl_sift@0.0.11/sift/src/Dictionary/keys.lua"]},{"name":"map","className":"ModuleScript","filePaths":["Packages/_Index/csqrl_sift@0.0.11/sift/src/Dictionary/map.lua"]},{"name":"merge","className":"ModuleScript","filePaths":["Packages/_Index/csqrl_sift@0.0.11/sift/src/Dictionary/merge.lua"]},{"name":"mergeDeep","className":"ModuleScript","filePaths":["Packages/_Index/csqrl_sift@0.0.11/sift/src/Dictionary/mergeDeep.lua"]},{"name":"removeKey","className":"ModuleScript","filePaths":["Packages/_Index/csqrl_sift@0.0.11/sift/src/Dictionary/removeKey.lua"]},{"name":"removeKeys","className":"ModuleScript","filePaths":["Packages/_Index/csqrl_sift@0.0.11/sift/src/Dictionary/removeKeys.lua"]},{"name":"removeValue","className":"ModuleScript","filePaths":["Packages/_Index/csqrl_sift@0.0.11/sift/src/Dictionary/removeValue.lua"]},{"name":"removeValues","className":"ModuleScript","filePaths":["Packages/_Index/csqrl_sift@0.0.11/sift/src/Dictionary/removeValues.lua"]},{"name":"set","className":"ModuleScript","filePaths":["Packages/_Index/csqrl_sift@0.0.11/sift/src/Dictionary/set.lua"]},{"name":"some","className":"ModuleScript","filePaths":["Packages/_Index/csqrl_sift@0.0.11/sift/src/Dictionary/some.lua"]},{"name":"update","className":"ModuleScript","filePaths":["Packages/_Index/csqrl_sift@0.0.11/sift/src/Dictionary/update.lua"]},{"name":"values","className":"ModuleScript","filePaths":["Packages/_Index/csqrl_sift@0.0.11/sift/src/Dictionary/values.lua"]},{"name":"withKeys","className":"ModuleScript","filePaths":["Packages/_Index/csqrl_sift@0.0.11/sift/src/Dictionary/withKeys.lua"]}]},{"name":"None","className":"ModuleScript","filePaths":["Packages/_Index/csqrl_sift@0.0.11/sift/src/None.lua"]},{"name":"Set","className":"ModuleScript","filePaths":["Packages/_Index/csqrl_sift@0.0.11/sift/src/Set/init.lua"],"children":[{"name":"add","className":"ModuleScript","filePaths":["Packages/_Index/csqrl_sift@0.0.11/sift/src/Set/add.lua"]},{"name":"copy","className":"ModuleScript","filePaths":["Packages/_Index/csqrl_sift@0.0.11/sift/src/Set/copy.lua"]},{"name":"count","className":"ModuleScript","filePaths":["Packages/_Index/csqrl_sift@0.0.11/sift/src/Set/count.lua"]},{"name":"delete","className":"ModuleScript","filePaths":["Packages/_Index/csqrl_sift@0.0.11/sift/src/Set/delete.lua"]},{"name":"difference","className":"ModuleScript","filePaths":["Packages/_Index/csqrl_sift@0.0.11/sift/src/Set/difference.lua"]},{"name":"differenceSymmetric","className":"ModuleScript","filePaths":["Packages/_Index/csqrl_sift@0.0.11/sift/src/Set/differenceSymmetric.lua"]},{"name":"filter","className":"ModuleScript","filePaths":["Packages/_Index/csqrl_sift@0.0.11/sift/src/Set/filter.lua"]},{"name":"fromArray","className":"ModuleScript","filePaths":["Packages/_Index/csqrl_sift@0.0.11/sift/src/Set/fromArray.lua"]},{"name":"has","className":"ModuleScript","filePaths":["Packages/_Index/csqrl_sift@0.0.11/sift/src/Set/has.lua"]},{"name":"intersection","className":"ModuleScript","filePaths":["Packages/_Index/csqrl_sift@0.0.11/sift/src/Set/intersection.lua"]},{"name":"isSubset","className":"ModuleScript","filePaths":["Packages/_Index/csqrl_sift@0.0.11/sift/src/Set/isSubset.lua"]},{"name":"isSuperset","className":"ModuleScript","filePaths":["Packages/_Index/csqrl_sift@0.0.11/sift/src/Set/isSuperset.lua"]},{"name":"map","className":"ModuleScript","filePaths":["Packages/_Index/csqrl_sift@0.0.11/sift/src/Set/map.lua"]},{"name":"merge","className":"ModuleScript","filePaths":["Packages/_Index/csqrl_sift@0.0.11/sift/src/Set/merge.lua"]},{"name":"toArray","className":"ModuleScript","filePaths":["Packages/_Index/csqrl_sift@0.0.11/sift/src/Set/toArray.lua"]}]},{"name":"Types","className":"ModuleScript","filePaths":["Packages/_Index/csqrl_sift@0.0.11/sift/src/Types.lua"]},{"name":"Util","className":"ModuleScript","filePaths":["Packages/_Index/csqrl_sift@0.0.11/sift/src/Util/init.lua"],"children":[{"name":"equalObjects","className":"ModuleScript","filePaths":["Packages/_Index/csqrl_sift@0.0.11/sift/src/Util/equalObjects.lua"]},{"name":"func","className":"ModuleScript","filePaths":["Packages/_Index/csqrl_sift@0.0.11/sift/src/Util/func.lua"]},{"name":"isEmpty","className":"ModuleScript","filePaths":["Packages/_Index/csqrl_sift@0.0.11/sift/src/Util/isEmpty.lua"]}]}]}]},{"name":"evaera_promise@4.0.0","className":"Folder","children":[{"name":"promise","className":"ModuleScript","filePaths":["Packages/_Index/evaera_promise@4.0.0/promise/lib/init.lua","Packages/_Index/evaera_promise@4.0.0/promise/default.project.json"],"children":[{"name":"init.spec","className":"ModuleScript","filePaths":["Packages/_Index/evaera_promise@4.0.0/promise/lib/init.spec.lua"]}]}]},{"name":"latte-soft_lucide-icons@0.1.3","className":"Folder","children":[{"name":"lucide-icons","className":"ModuleScript","filePaths":["Packages/_Index/latte-soft_lucide-icons@0.1.3/lucide-icons/lib/init.luau","Packages/_Index/latte-soft_lucide-icons@0.1.3/lucide-icons/default.project.json"],"children":[{"name":"Icons","className":"ModuleScript","filePaths":["Packages/_Index/latte-soft_lucide-icons@0.1.3/lucide-icons/lib/Icons.luau"]},{"name":"VersionInfo","className":"ModuleScript","filePaths":["Packages/_Index/latte-soft_lucide-icons@0.1.3/lucide-icons/version-info.luau"]}]}]},{"name":"littensy_charm@0.10.0","className":"Folder","children":[{"name":"charm","className":"ModuleScript","filePaths":["Packages/_Index/littensy_charm@0.10.0/charm/init.luau"],"children":[{"name":"src","className":"ModuleScript","filePaths":["Packages/_Index/littensy_charm@0.10.0/charm/src/init.luau"],"children":[{"name":"atom","className":"ModuleScript","filePaths":["Packages/_Index/littensy_charm@0.10.0/charm/src/atom.luau"]},{"name":"computed","className":"ModuleScript","filePaths":["Packages/_Index/littensy_charm@0.10.0/charm/src/computed.luau"]},{"name":"effect","className":"ModuleScript","filePaths":["Packages/_Index/littensy_charm@0.10.0/charm/src/effect.luau"]},{"name":"mapped","className":"ModuleScript","filePaths":["Packages/_Index/littensy_charm@0.10.0/charm/src/mapped.luau"]},{"name":"observe","className":"ModuleScript","filePaths":["Packages/_Index/littensy_charm@0.10.0/charm/src/observe.luau"]},{"name":"store","className":"ModuleScript","filePaths":["Packages/_Index/littensy_charm@0.10.0/charm/src/store.luau"]},{"name":"subscribe","className":"ModuleScript","filePaths":["Packages/_Index/littensy_charm@0.10.0/charm/src/subscribe.luau"]},{"name":"types","className":"ModuleScript","filePaths":["Packages/_Index/littensy_charm@0.10.0/charm/src/types.luau"]}]},{"name":"wally","className":"ModuleScript","filePaths":["Packages/_Index/littensy_charm@0.10.0/charm/wally.toml"]}]}]},{"name":"littensy_remo@1.5.3","className":"Folder","children":[{"name":"Promise","className":"ModuleScript","filePaths":["Packages/_Index/littensy_remo@1.5.3/Promise.lua"]},{"name":"remo","className":"ModuleScript","filePaths":["Packages/_Index/littensy_remo@1.5.3/remo/src/init.luau","Packages/_Index/littensy_remo@1.5.3/remo/default.project.json"],"children":[{"name":"Promise","className":"ModuleScript","filePaths":["Packages/_Index/littensy_remo@1.5.3/remo/src/Promise.luau"]},{"name":"builder","className":"ModuleScript","filePaths":["Packages/_Index/littensy_remo@1.5.3/remo/src/builder.luau"]},{"name":"client","className":"ModuleScript","filePaths":["Packages/_Index/littensy_remo@1.5.3/remo/src/client/init.luau"],"children":[{"name":"createAsyncRemote","className":"ModuleScript","filePaths":["Packages/_Index/littensy_remo@1.5.3/remo/src/client/createAsyncRemote.luau"]},{"name":"createAsyncRemote.spec","className":"ModuleScript","filePaths":["Packages/_Index/littensy_remo@1.5.3/remo/src/client/createAsyncRemote.spec.luau"]},{"name":"createRemote","className":"ModuleScript","filePaths":["Packages/_Index/littensy_remo@1.5.3/remo/src/client/createRemote.luau"]},{"name":"createRemote.spec","className":"ModuleScript","filePaths":["Packages/_Index/littensy_remo@1.5.3/remo/src/client/createRemote.spec.luau"]}]},{"name":"constants","className":"ModuleScript","filePaths":["Packages/_Index/littensy_remo@1.5.3/remo/src/constants.luau"]},{"name":"container","className":"Configuration","filePaths":["Packages/_Index/littensy_remo@1.5.3/remo/src/container/init.meta.json"]},{"name":"createRemotes","className":"ModuleScript","filePaths":["Packages/_Index/littensy_remo@1.5.3/remo/src/createRemotes.luau"]},{"name":"createRemotes.spec","className":"ModuleScript","filePaths":["Packages/_Index/littensy_remo@1.5.3/remo/src/createRemotes.spec.luau"]},{"name":"getSender","className":"ModuleScript","filePaths":["Packages/_Index/littensy_remo@1.5.3/remo/src/getSender.luau"]},{"name":"init.spec","className":"ModuleScript","filePaths":["Packages/_Index/littensy_remo@1.5.3/remo/src/init.spec.luau"]},{"name":"middleware","className":"Folder","children":[{"name":"loggerMiddleware","className":"ModuleScript","filePaths":["Packages/_Index/littensy_remo@1.5.3/remo/src/middleware/loggerMiddleware.luau"]},{"name":"throttleMiddleware","className":"ModuleScript","filePaths":["Packages/_Index/littensy_remo@1.5.3/remo/src/middleware/throttleMiddleware.luau"]},{"name":"throttleMiddleware.spec","className":"ModuleScript","filePaths":["Packages/_Index/littensy_remo@1.5.3/remo/src/middleware/throttleMiddleware.spec.luau"]}]},{"name":"server","className":"ModuleScript","filePaths":["Packages/_Index/littensy_remo@1.5.3/remo/src/server/init.luau"],"children":[{"name":"createAsyncRemote","className":"ModuleScript","filePaths":["Packages/_Index/littensy_remo@1.5.3/remo/src/server/createAsyncRemote.luau"]},{"name":"createAsyncRemote.spec","className":"ModuleScript","filePaths":["Packages/_Index/littensy_remo@1.5.3/remo/src/server/createAsyncRemote.spec.luau"]},{"name":"createRemote","className":"ModuleScript","filePaths":["Packages/_Index/littensy_remo@1.5.3/remo/src/server/createRemote.luau"]},{"name":"createRemote.spec","className":"ModuleScript","filePaths":["Packages/_Index/littensy_remo@1.5.3/remo/src/server/createRemote.spec.luau"]}]},{"name":"types","className":"ModuleScript","filePaths":["Packages/_Index/littensy_remo@1.5.3/remo/src/types.luau"]},{"name":"utils","className":"Folder","children":[{"name":"compose","className":"ModuleScript","filePaths":["Packages/_Index/littensy_remo@1.5.3/remo/src/utils/compose.luau"]},{"name":"compose.spec","className":"ModuleScript","filePaths":["Packages/_Index/littensy_remo@1.5.3/remo/src/utils/compose.spec.luau"]},{"name":"instances","className":"ModuleScript","filePaths":["Packages/_Index/littensy_remo@1.5.3/remo/src/utils/instances.luau"]},{"name":"mockRemotes","className":"ModuleScript","filePaths":["Packages/_Index/littensy_remo@1.5.3/remo/src/utils/mockRemotes.luau"]},{"name":"mockRemotes.spec","className":"ModuleScript","filePaths":["Packages/_Index/littensy_remo@1.5.3/remo/src/utils/mockRemotes.spec.luau"]},{"name":"testRemote","className":"ModuleScript","filePaths":["Packages/_Index/littensy_remo@1.5.3/remo/src/utils/testRemote.luau"]},{"name":"unwrap","className":"ModuleScript","filePaths":["Packages/_Index/littensy_remo@1.5.3/remo/src/utils/unwrap.luau"]}]}]}]},{"name":"littensy_vide-charm@0.3.0","className":"Folder","children":[{"name":"Vide","className":"ModuleScript","filePaths":["Packages/_Index/littensy_vide-charm@0.3.0/Vide.lua"]},{"name":"charm","className":"ModuleScript","filePaths":["Packages/_Index/littensy_vide-charm@0.3.0/charm.lua"]},{"name":"vide-charm","className":"ModuleScript","filePaths":["Packages/_Index/littensy_vide-charm@0.3.0/vide-charm/init.luau"],"children":[{"name":"src","className":"ModuleScript","filePaths":["Packages/_Index/littensy_vide-charm@0.3.0/vide-charm/src/init.luau"]},{"name":"wally","className":"ModuleScript","filePaths":["Packages/_Index/littensy_vide-charm@0.3.0/vide-charm/wally.toml"]}]}]},{"name":"maximumadhd_promise-typed@1.0.0","className":"Folder","children":[{"name":"PromiseBase","className":"ModuleScript","filePaths":["Packages/_Index/maximumadhd_promise-typed@1.0.0/PromiseBase.lua"]},{"name":"promise-typed","className":"ModuleScript","filePaths":["Packages/_Index/maximumadhd_promise-typed@1.0.0/promise-typed/init.luau"],"children":[{"name":"wally","className":"ModuleScript","filePaths":["Packages/_Index/maximumadhd_promise-typed@1.0.0/promise-typed/wally.toml"]}]}]},{"name":"megamonsta2_fastcast@1.0.0","className":"Folder","children":[{"name":"PartCache","className":"ModuleScript","filePaths":["Packages/_Index/megamonsta2_fastcast@1.0.0/PartCache.lua"]},{"name":"Table","className":"ModuleScript","filePaths":["Packages/_Index/megamonsta2_fastcast@1.0.0/Table.lua"]},{"name":"fastcast","className":"ModuleScript","filePaths":["Packages/_Index/megamonsta2_fastcast@1.0.0/fastcast/src/init.luau","Packages/_Index/megamonsta2_fastcast@1.0.0/fastcast/default.project.json"],"children":[{"name":"ActiveCast","className":"ModuleScript","filePaths":["Packages/_Index/megamonsta2_fastcast@1.0.0/fastcast/src/ActiveCast.luau"]},{"name":"Config","className":"ModuleScript","filePaths":["Packages/_Index/megamonsta2_fastcast@1.0.0/fastcast/src/Config.luau"]},{"name":"Events","className":"ModuleScript","filePaths":["Packages/_Index/megamonsta2_fastcast@1.0.0/fastcast/src/Events.luau"]},{"name":"Signal","className":"ModuleScript","filePaths":["Packages/_Index/megamonsta2_fastcast@1.0.0/fastcast/src/Signal.luau"]},{"name":"TypeDefinitions","className":"ModuleScript","filePaths":["Packages/_Index/megamonsta2_fastcast@1.0.0/fastcast/src/TypeDefinitions.luau"]},{"name":"TypeMarshaller","className":"ModuleScript","filePaths":["Packages/_Index/megamonsta2_fastcast@1.0.0/fastcast/src/TypeMarshaller.luau"]}]}]},{"name":"megamonsta2_partcache@1.1.3","className":"Folder","children":[{"name":"Table","className":"ModuleScript","filePaths":["Packages/_Index/megamonsta2_partcache@1.1.3/Table.lua"]},{"name":"partcache","className":"ModuleScript","filePaths":["Packages/_Index/megamonsta2_partcache@1.1.3/partcache/src/init.luau","Packages/_Index/megamonsta2_partcache@1.1.3/partcache/default.project.json"],"children":[{"name":"Class","className":"ModuleScript","filePaths":["Packages/_Index/megamonsta2_partcache@1.1.3/partcache/src/Class.luau"]}]}]},{"name":"megamonsta2_table@1.0.3","className":"Folder","children":[{"name":"table","className":"ModuleScript","filePaths":["Packages/_Index/megamonsta2_table@1.0.3/table/src/init.luau","Packages/_Index/megamonsta2_table@1.0.3/table/default.project.json"]}]},{"name":"osyrisrblx_t@3.1.1","className":"Folder","children":[{"name":"t","className":"ModuleScript","filePaths":["Packages/_Index/osyrisrblx_t@3.1.1/t/lib/init.lua","Packages/_Index/osyrisrblx_t@3.1.1/t/default.project.json"]}]},{"name":"paradoxum-games_lyra@0.6.0","className":"Folder","children":[{"name":"Promise","className":"ModuleScript","filePaths":["Packages/_Index/paradoxum-games_lyra@0.6.0/Promise.lua"]},{"name":"lyra","className":"ModuleScript","filePaths":["Packages/_Index/paradoxum-games_lyra@0.6.0/lyra/src/init.luau","Packages/_Index/paradoxum-games_lyra@0.6.0/lyra/default.project.json"],"children":[{"name":"Constants","className":"ModuleScript","filePaths":["Packages/_Index/paradoxum-games_lyra@0.6.0/lyra/src/Constants.luau"]},{"name":"Files","className":"ModuleScript","filePaths":["Packages/_Index/paradoxum-games_lyra@0.6.0/lyra/src/Files.luau"]},{"name":"JsonPatch","className":"ModuleScript","filePaths":["Packages/_Index/paradoxum-games_lyra@0.6.0/lyra/src/JsonPatch.luau"]},{"name":"Locks","className":"ModuleScript","filePaths":["Packages/_Index/paradoxum-games_lyra@0.6.0/lyra/src/Locks.luau"]},{"name":"Log","className":"ModuleScript","filePaths":["Packages/_Index/paradoxum-games_lyra@0.6.0/lyra/src/Log.luau"]},{"name":"Migrations","className":"ModuleScript","filePaths":["Packages/_Index/paradoxum-games_lyra@0.6.0/lyra/src/Migrations.luau"]},{"name":"MockDataStoreService","className":"ModuleScript","filePaths":["Packages/_Index/paradoxum-games_lyra@0.6.0/lyra/src/MockDataStoreService.luau"]},{"name":"MockMemoryStoreService","className":"ModuleScript","filePaths":["Packages/_Index/paradoxum-games_lyra@0.6.0/lyra/src/MockMemoryStoreService.luau"]},{"name":"PlayerStore","className":"ModuleScript","filePaths":["Packages/_Index/paradoxum-games_lyra@0.6.0/lyra/src/PlayerStore.luau"]},{"name":"Promise","className":"ModuleScript","filePaths":["Packages/_Index/paradoxum-games_lyra@0.6.0/lyra/src/Promise.luau"]},{"name":"PromiseQueue","className":"ModuleScript","filePaths":["Packages/_Index/paradoxum-games_lyra@0.6.0/lyra/src/PromiseQueue.luau"]},{"name":"Session","className":"ModuleScript","filePaths":["Packages/_Index/paradoxum-games_lyra@0.6.0/lyra/src/Session.luau"]},{"name":"Store","className":"ModuleScript","filePaths":["Packages/_Index/paradoxum-games_lyra@0.6.0/lyra/src/Store.luau"]},{"name":"Tables","className":"ModuleScript","filePaths":["Packages/_Index/paradoxum-games_lyra@0.6.0/lyra/src/Tables.luau"]},{"name":"Transactions","className":"ModuleScript","filePaths":["Packages/_Index/paradoxum-games_lyra@0.6.0/lyra/src/Transactions.luau"]},{"name":"Types","className":"ModuleScript","filePaths":["Packages/_Index/paradoxum-games_lyra@0.6.0/lyra/src/Types.luau"]},{"name":"dataStoreRetry","className":"ModuleScript","filePaths":["Packages/_Index/paradoxum-games_lyra@0.6.0/lyra/src/dataStoreRetry.luau"]},{"name":"hashMapRetry","className":"ModuleScript","filePaths":["Packages/_Index/paradoxum-games_lyra@0.6.0/lyra/src/hashMapRetry.luau"]},{"name":"noYield","className":"ModuleScript","filePaths":["Packages/_Index/paradoxum-games_lyra@0.6.0/lyra/src/noYield.luau"]}]},{"name":"t","className":"ModuleScript","filePaths":["Packages/_Index/paradoxum-games_lyra@0.6.0/t.lua"]}]},{"name":"sirmallard_iris@2.5.0","className":"Folder","children":[{"name":"iris","className":"ModuleScript","filePaths":["Packages/_Index/sirmallard_iris@2.5.0/iris/lib/init.lua","Packages/_Index/sirmallard_iris@2.5.0/iris/default.project.json"],"children":[{"name":"API","className":"ModuleScript","filePaths":["Packages/_Index/sirmallard_iris@2.5.0/iris/lib/API.lua"]},{"name":"Internal","className":"ModuleScript","filePaths":["Packages/_Index/sirmallard_iris@2.5.0/iris/lib/Internal.lua"]},{"name":"PubTypes","className":"ModuleScript","filePaths":["Packages/_Index/sirmallard_iris@2.5.0/iris/lib/PubTypes.lua"]},{"name":"Types","className":"ModuleScript","filePaths":["Packages/_Index/sirmallard_iris@2.5.0/iris/lib/Types.lua"]},{"name":"WidgetTypes","className":"ModuleScript","filePaths":["Packages/_Index/sirmallard_iris@2.5.0/iris/lib/WidgetTypes.lua"]},{"name":"config","className":"ModuleScript","filePaths":["Packages/_Index/sirmallard_iris@2.5.0/iris/lib/config.lua"]},{"name":"demoWindow","className":"ModuleScript","filePaths":["Packages/_Index/sirmallard_iris@2.5.0/iris/lib/demoWindow.lua"]},{"name":"widgets","className":"ModuleScript","filePaths":["Packages/_Index/sirmallard_iris@2.5.0/iris/lib/widgets/init.lua"],"children":[{"name":"Button","className":"ModuleScript","filePaths":["Packages/_Index/sirmallard_iris@2.5.0/iris/lib/widgets/Button.lua"]},{"name":"Checkbox","className":"ModuleScript","filePaths":["Packages/_Index/sirmallard_iris@2.5.0/iris/lib/widgets/Checkbox.lua"]},{"name":"Combo","className":"ModuleScript","filePaths":["Packages/_Index/sirmallard_iris@2.5.0/iris/lib/widgets/Combo.lua"]},{"name":"Format","className":"ModuleScript","filePaths":["Packages/_Index/sirmallard_iris@2.5.0/iris/lib/widgets/Format.lua"]},{"name":"Image","className":"ModuleScript","filePaths":["Packages/_Index/sirmallard_iris@2.5.0/iris/lib/widgets/Image.lua"]},{"name":"Input","className":"ModuleScript","filePaths":["Packages/_Index/sirmallard_iris@2.5.0/iris/lib/widgets/Input.lua"]},{"name":"Menu","className":"ModuleScript","filePaths":["Packages/_Index/sirmallard_iris@2.5.0/iris/lib/widgets/Menu.lua"]},{"name":"Plot","className":"ModuleScript","filePaths":["Packages/_Index/sirmallard_iris@2.5.0/iris/lib/widgets/Plot.lua"]},{"name":"RadioButton","className":"ModuleScript","filePaths":["Packages/_Index/sirmallard_iris@2.5.0/iris/lib/widgets/RadioButton.lua"]},{"name":"Root","className":"ModuleScript","filePaths":["Packages/_Index/sirmallard_iris@2.5.0/iris/lib/widgets/Root.lua"]},{"name":"Tab","className":"ModuleScript","filePaths":["Packages/_Index/sirmallard_iris@2.5.0/iris/lib/widgets/Tab.lua"]},{"name":"Table","className":"ModuleScript","filePaths":["Packages/_Index/sirmallard_iris@2.5.0/iris/lib/widgets/Table.lua"]},{"name":"Text","className":"ModuleScript","filePaths":["Packages/_Index/sirmallard_iris@2.5.0/iris/lib/widgets/Text.lua"]},{"name":"Tree","className":"ModuleScript","filePaths":["Packages/_Index/sirmallard_iris@2.5.0/iris/lib/widgets/Tree.lua"]},{"name":"Window","className":"ModuleScript","filePaths":["Packages/_Index/sirmallard_iris@2.5.0/iris/lib/widgets/Window.lua"]}]}]}]},{"name":"sleitnick_component@2.4.8","className":"Folder","children":[{"name":"Promise","className":"ModuleScript","filePaths":["Packages/_Index/sleitnick_component@2.4.8/Promise.lua"]},{"name":"Signal","className":"ModuleScript","filePaths":["Packages/_Index/sleitnick_component@2.4.8/Signal.lua"]},{"name":"Symbol","className":"ModuleScript","filePaths":["Packages/_Index/sleitnick_component@2.4.8/Symbol.lua"]},{"name":"Trove","className":"ModuleScript","filePaths":["Packages/_Index/sleitnick_component@2.4.8/Trove.lua"]},{"name":"component","className":"ModuleScript","filePaths":["Packages/_Index/sleitnick_component@2.4.8/component/init.lua"],"children":[{"name":"init.spec","className":"ModuleScript","filePaths":["Packages/_Index/sleitnick_component@2.4.8/component/init.spec.lua"]},{"name":"wally","className":"ModuleScript","filePaths":["Packages/_Index/sleitnick_component@2.4.8/component/wally.toml"]}]}]},{"name":"sleitnick_loader@2.0.0","className":"Folder","children":[{"name":"loader","className":"ModuleScript","filePaths":["Packages/_Index/sleitnick_loader@2.0.0/loader/init.lua"],"children":[{"name":"wally","className":"ModuleScript","filePaths":["Packages/_Index/sleitnick_loader@2.0.0/loader/wally.toml"]}]}]},{"name":"sleitnick_signal@2.0.3","className":"Folder","children":[{"name":"signal","className":"ModuleScript","filePaths":["Packages/_Index/sleitnick_signal@2.0.3/signal/init.luau"],"children":[{"name":"init.test","className":"ModuleScript","filePaths":["Packages/_Index/sleitnick_signal@2.0.3/signal/init.test.luau"]},{"name":"wally","className":"ModuleScript","filePaths":["Packages/_Index/sleitnick_signal@2.0.3/signal/wally.toml"]}]}]},{"name":"sleitnick_symbol@2.0.1","className":"Folder","children":[{"name":"symbol","className":"ModuleScript","filePaths":["Packages/_Index/sleitnick_symbol@2.0.1/symbol/init.lua"],"children":[{"name":"init.spec","className":"ModuleScript","filePaths":["Packages/_Index/sleitnick_symbol@2.0.1/symbol/init.spec.lua"]},{"name":"wally","className":"ModuleScript","filePaths":["Packages/_Index/sleitnick_symbol@2.0.1/symbol/wally.toml"]}]}]},{"name":"sleitnick_trove@1.8.0","className":"Folder","children":[{"name":"trove","className":"ModuleScript","filePaths":["Packages/_Index/sleitnick_trove@1.8.0/trove/init.luau"],"children":[{"name":"init.test","className":"ModuleScript","filePaths":["Packages/_Index/sleitnick_trove@1.8.0/trove/init.test.luau"]},{"name":"wally","className":"ModuleScript","filePaths":["Packages/_Index/sleitnick_trove@1.8.0/trove/wally.toml"]}]}]}]}]}]},{"name":"ServerScriptService","className":"ServerScriptService","children":[{"name":"Server","className":"Script","filePaths":["src/server/init.meta.json","src/server/init.server.luau"],"children":[{"name":"Components","className":"Folder","children":[{"name":"FoodItem","className":"ModuleScript","filePaths":["src/server/Components/FoodItem.luau"]},{"name":"ToolGiver","className":"ModuleScript","filePaths":["src/server/Components/ToolGiver.luau"]}]},{"name":"Modules","className":"Folder","children":[{"name":"_types","className":"ModuleScript","filePaths":["src/server/Modules/_types.luau"]}]},{"name":"Services","className":"Folder","children":[{"name":"CashDropperService","className":"ModuleScript","filePaths":["src/server/Services/CashDropperService/init.luau"],"children":[{"name":"CashDrop","className":"ModuleScript","filePaths":["src/server/Services/CashDropperService/CashDrop.luau"]},{"name":"CashDropperService","className":"ModuleScript","filePaths":["src/server/Services/CashDropperService/CashDropperService.luau"]}]},{"name":"ConchServerService","className":"ModuleScript","filePaths":["src/server/Services/ConchServerService/init.luau"],"children":[{"name":"Commands","className":"Folder","children":[{"name":"ban","className":"ModuleScript","filePaths":["src/server/Services/ConchServerService/Commands/ban.luau"]},{"name":"getbanhistory","className":"ModuleScript","filePaths":["src/server/Services/ConchServerService/Commands/getbanhistory.luau"]},{"name":"givecash","className":"ModuleScript","filePaths":["src/server/Services/ConchServerService/Commands/givecash.luau"]},{"name":"kick","className":"ModuleScript","filePaths":["src/server/Services/ConchServerService/Commands/kick.luau"]},{"name":"setcash","className":"ModuleScript","filePaths":["src/server/Services/ConchServerService/Commands/setcash.luau"]},{"name":"unban","className":"ModuleScript","filePaths":["src/server/Services/ConchServerService/Commands/unban.luau"]}]}]},{"name":"DataService","className":"ModuleScript","filePaths":["src/server/Services/DataService/init.luau"]},{"name":"NetworkService","className":"Folder","children":[{"name":"Events","className":"Folder"},{"name":"Functions","className":"Folder","children":[{"name":"PunishPlayer","className":"ModuleScript","filePaths":["src/server/Services/NetworkService/Functions/PunishPlayer.luau"]},{"name":"WalletDropCash","className":"ModuleScript","filePaths":["src/server/Services/NetworkService/Functions/WalletDropCash.luau"]}]}]},{"name":"PunishmentService","className":"ModuleScript","filePaths":["src/server/Services/PunishmentService.luau"]},{"name":"World","className":"Folder","children":[{"name":"RobbableService","className":"ModuleScript","filePaths":["src/server/Services/World/RobbableService.luau"]},{"name":"WeaponServerService","className":"ModuleScript","filePaths":["src/server/Services/World/WeaponServerService.luau"]}]}]}]}]},{"name":"SoundService","className":"SoundService"},{"name":"StarterPack","className":"StarterPack","filePaths":["src/starter-pack/init.meta.json"],"children":[{"name":"RPG","className":"Tool","filePaths":["src/starter-pack/RPG/init.meta.json"]},{"name":"Revolver","className":"Tool","filePaths":["src/starter-pack/Revolver/init.meta.json"]},{"name":"Wallet","className":"Tool","filePaths":["src/starter-pack/Wallet/init.meta.json"],"children":[{"name":"Wallet","className":"LocalScript","filePaths":["src/starter-pack/Wallet/Wallet.client.luau"]},{"name":"WalletBillboard","className":"Script","filePaths":["src/starter-pack/Wallet/WalletBillboard.server.luau"]}]}]},{"name":"StarterPlayer","className":"StarterPlayer","children":[{"name":"StarterCharacterScripts","className":"StarterCharacterScripts","filePaths":["src/starter-character/init.meta.json"],"children":[{"name":"Antivoid","className":"Script","filePaths":["src/starter-character/Antivoid.server.luau"]},{"name":"Ragdoll","className":"LocalScript","filePaths":["src/starter-character/Ragdoll.client.luau"]},{"name":"RagdollDeath","className":"Script","filePaths":["src/starter-character/RagdollDeath.server.luau"]}]},{"name":"StarterPlayerScripts","className":"StarterPlayerScripts","children":[{"name":"Client","className":"LocalScript","filePaths":["src/client/init.meta.json","src/client/init.client.luau"],"children":[{"name":"ButtonClickHandler","className":"LocalScript","filePaths":["src/client/ButtonClickHandler.client.luau"]},{"name":"Services","className":"Folder","children":[{"name":"ConchClientService","className":"ModuleScript","filePaths":["src/client/Services/ConchClientService/init.luau"],"children":[{"name":"Commands","className":"Folder","children":[{"name":"punish","className":"ModuleScript","filePaths":["src/client/Services/ConchClientService/Commands/punish.luau"]}]}]},{"name":"IrisService","className":"ModuleScript","filePaths":["src/client/Services/IrisService/init.luau"],"children":[{"name":"PunishmentPanel","className":"ModuleScript","filePaths":["src/client/Services/IrisService/PunishmentPanel.luau"]}]},{"name":"WeaponClientService","className":"ModuleScript","filePaths":["src/client/Services/WeaponClientService.luau"]}]}]}]}]},{"name":"Workspace","className":"Workspace","children":[{"name":"Baseplate","className":"Part"}]}]}